storyville/__init__.py
storyville/__main__.py
storyville/app.py
storyville/assertions/__init__.py
storyville/assertions/helpers.py
storyville/build.py
storyville/catalog/__init__.py
storyville/catalog/helpers.py
storyville/catalog/models.py
storyville/catalog/views.py
storyville/components/__init__.py
storyville/components/aside/__init__.py
storyville/components/aside/aside.py
storyville/components/aside/aside_test.py
storyville/components/breadcrumbs/__init__.py
storyville/components/breadcrumbs/breadcrumbs.py
storyville/components/breadcrumbs/breadcrumbs_test.py
storyville/components/footer/__init__.py
storyville/components/footer/footer.py
storyville/components/footer/footer_test.py
storyville/components/header/__init__.py
storyville/components/header/header.py
storyville/components/header/header_test.py
storyville/components/layout/__init__.py
storyville/components/layout/layout.py
storyville/components/layout/layout_test.py
storyville/components/layout/static/favicon.ico
storyville/components/layout/static/favicon.svg
storyville/components/layout/static/idiomorph.js
storyville/components/layout/static/pico-docs.css
storyville/components/layout/static/pico-main.css
storyville/components/layout/static/sidebar.mjs
storyville/components/layout/static/storyville.css
storyville/components/layout/static/tree-expand.mjs
storyville/components/layout/static/ws.mjs
storyville/components/layout/stories.py
storyville/components/layout/test_components_listing.py
storyville/components/main/__init__.py
storyville/components/main/main.py
storyville/components/main/main_test.py
storyville/components/navigation_tree/__init__.py
storyville/components/navigation_tree/navigation_tree.py
storyville/components/navigation_tree/navigation_tree_test.py
storyville/components/sections_listing/__init__.py
storyville/components/sections_listing/stories.py
storyville/components/stories.py
storyville/components/themed_story/__init__.py
storyville/components/themed_story/themed_story.py
storyville-0.1.1.dist-info/WHEEL
storyville-0.1.1.dist-info/entry_points.txt
storyville-0.1.1.dist-info/METADATA
storyville-0.1.1.dist-info/RECORD
