Metadata-Version: 2.4
Name: storyville
Version: 0.1.1
Summary: Story-based component development for Python.
Author: Paul Everitt
Author-email: Paul Everitt <pauleveritt@me.com>
License-Expression: MIT
Classifier: Development Status :: 3 - Alpha
Classifier: Programming Language :: Python :: 3.14
Requires-Dist: starlette>=0.50.0
Requires-Dist: tdom
Requires-Dist: typer>=0.20.0
Requires-Dist: uvicorn[standard]>=0.38.0
Requires-Dist: watchfiles>=1.1.1
Requires-Python: >=3.14
